covid19_id/__init__.py
covid19_id/__main__.py
covid19_id/covid19_id.py
covid19_id/data/__init__.py
covid19_id/data/data.py
covid19_id/data/data_key_doc.py
covid19_id/data/kasus/__init__.py
covid19_id/data/kasus/base.py
covid19_id/data/kasus/gejala.py
covid19_id/data/kasus/jenis_kelamin.py
covid19_id/data/kasus/kasus.py
covid19_id/data/kasus/kelompok_umur.py
covid19_id/data/kasus/kondisi_penyerta.py
covid19_id/data/meninggal/__init__.py
covid19_id/data/meninggal/base.py
covid19_id/data/meninggal/gejala.py
covid19_id/data/meninggal/jenis_kelamin.py
covid19_id/data/meninggal/kelompok_umur.py
covid19_id/data/meninggal/kondisi_penyerta.py
covid19_id/data/meninggal/meninggal.py
covid19_id/data/perawatan/__init__.py
covid19_id/data/perawatan/base.py
covid19_id/data/perawatan/gejala.py
covid19_id/data/perawatan/jenis_kelamin.py
covid19_id/data/perawatan/kelompok_umur.py
covid19_id/data/perawatan/kondisi_penyerta.py
covid19_id/data/perawatan/perawatan.py
covid19_id/data/sembuh/__init__.py
covid19_id/data/sembuh/base.py
covid19_id/data/sembuh/gejala.py
covid19_id/data/sembuh/jenis_kelamin.py
covid19_id/data/sembuh/kelompok_umur.py
covid19_id/data/sembuh/kondisi_penyerta.py
covid19_id/data/sembuh/sembuh.py
covid19_id/pemeriksaan_vaksinasi/__init__.py
covid19_id/pemeriksaan_vaksinasi/pemeriksaan.py
covid19_id/pemeriksaan_vaksinasi/pemeriksaan_harian.py
covid19_id/pemeriksaan_vaksinasi/pemeriksaan_vaksinasi.py
covid19_id/pemeriksaan_vaksinasi/penambahan_pemeriksaan.py
covid19_id/pemeriksaan_vaksinasi/penambahan_vaksinasi.py
covid19_id/pemeriksaan_vaksinasi/total_pemeriksaan.py
covid19_id/pemeriksaan_vaksinasi/total_vaksinasi.py
covid19_id/pemeriksaan_vaksinasi/vaksinasi.py
covid19_id/pemeriksaan_vaksinasi/vaksinasi_harian.py
covid19_id/provinsi/__init__.py
covid19_id/provinsi/data_provinsi.py
covid19_id/provinsi/jenis_kelamin.py
covid19_id/provinsi/kelompok_umur.py
covid19_id/provinsi/lokasi.py
covid19_id/provinsi/penambahan.py
covid19_id/provinsi/provinsi.py
covid19_id-1.1.0.dist-info/LICENSE
covid19_id-1.1.0.dist-info/WHEEL
covid19_id-1.1.0.dist-info/METADATA
covid19_id-1.1.0.dist-info/RECORD
