Metadata-Version: 2.1
Name: covid19-id
Version: 1.1.0
Summary: Python module for getting Indonesian covid19 data from covid19.go.id
Home-page: https://github.com/hexatester/covid19-id
License: MIT
Keywords: covid19,indonesia,api,covid-data
Author: hexatester
Author-email: hexatester@protonmail.com
Requires-Python: >=3.7,<4.0
Classifier: Development Status :: 5 - Production/Stable
Classifier: Intended Audience :: Developers
Classifier: License :: OSI Approved :: MIT License
Classifier: Operating System :: OS Independent
Classifier: Programming Language :: Python :: 3
Classifier: Programming Language :: Python :: 3.10
Classifier: Programming Language :: Python :: 3.7
Classifier: Programming Language :: Python :: 3.8
Classifier: Programming Language :: Python :: 3.9
Classifier: Topic :: Scientific/Engineering
Provides-Extra: ujson
Requires-Dist: attrs (>=20.3.0,<21.0.0)
Requires-Dist: cattrs (>=1.3.0,<2.0.0)
Requires-Dist: python-dateutil (>=2.8.1,<3.0.0)
Requires-Dist: ujson (>=4.0.2,<5.0.0); extra == "ujson"
Project-URL: Repository, https://github.com/hexatester/covid19-id
